{
    "userId": 1533100,
    "authorName": "Barbara Sheridan",
    "from": "Barbara Sheridan &lt;bsher213@...&gt;",
    "profile": "bsher213",
    "replyTo": "LIST",
    "senderId": "BblKUq3QZmx8VUFZlTaMtMYqUnivjlzfp6IGjEVM2Q7NyO2caa-nqiRIP6-DGErpKJ-Kr0Tcs4JlSbK32LqZB-PkUXo7cOOIuPcJG8g0Smsgi5o",
    "spamInfo": {
        "isSpam": false,
        "reason": "0"
    },
    "subject": "Re: [SHQ_Spy_Division] opinion of anime-fanfiction.net",
    "postDate": "1082505215",
    "msgId": 111,
    "canDelete": false,
    "contentTrasformed": false,
    "systemMessage": false,
    "headers": {
        "messageIdInHeader": "PDQwODVCN0ZGLjEwMDA2MDJAYmVsbGF0bGFudGljLm5ldD4=",
        "inReplyToHeader": "PDUuMS4wLjE0LjAuMjAwNDA0MjAxOTQyMzMuMDBiNDM1NzhAcG9wLm1pbmRzcHJpbmcuY29tPg==",
        "referencesHeader": "PDUuMS4wLjE0LjAuMjAwNDA0MjAxOTQyMzMuMDBiNDM1NzhAcG9wLm1pbmRzcHJpbmcuY29tPg=="
    },
    "prevInTopic": 110,
    "nextInTopic": 129,
    "prevInTime": 110,
    "nextInTime": 112,
    "topicId": 109,
    "numMessagesInTopic": 10,
    "msgSnippet": "The forum feature doesn t work *figures* and I m an idiot because I keep calling it anime-fanfiction when it s anime-fiction.net -- Barbara Sheridan ",
    "rawEmail": "Return-Path: &lt;bsher213@...&gt;\r\nX-Sender: bsher213@...\r\nX-Apparently-To: SHQ_Spy_Division@yahoogroups.com\r\nReceived: (qmail 73564 invoked from network); 20 Apr 2004 23:54:01 -0000\r\nReceived: from unknown (66.218.66.218)\n  by m22.grp.scd.yahoo.com with QMQP; 20 Apr 2004 23:54:01 -0000\r\nReceived: from unknown (HELO out011.verizon.net) (206.46.170.135)\n  by mta3.grp.scd.yahoo.com with SMTP; 20 Apr 2004 23:54:01 -0000\r\nReceived: from bellatlantic.net ([68.162.188.232]) by out011.verizon.net\n          (InterMail vM.5.01.06.06 201-253-122-130-106-20030910) with ESMTP\n          id &lt;20040420235335.GMHJ18566.out011.verizon.net@...&gt;\n          for &lt;SHQ_Spy_Division@yahoogroups.com&gt;;\n          Tue, 20 Apr 2004 18:53:35 -0500\r\nMessage-ID: &lt;4085B7FF.1000602@...&gt;\r\nDate: Tue, 20 Apr 2004 19:53:35 -0400\r\nUser-Agent: Mozilla/5.0 (Windows; U; Windows NT 5.1; en-US; rv:1.4) Gecko/20030624 Netscape/7.1 (ax)\r\nX-Accept-Language: en-us, en, ja\r\nMIME-Version: 1.0\r\nTo: SHQ_Spy_Division@yahoogroups.com\r\nReferences: &lt;5.1.0.14.0.20040420194233.00b43578@...&gt;\r\nIn-Reply-To: &lt;5.1.0.14.0.20040420194233.00b43578@...&gt;\r\nContent-Type: text/plain; charset=us-ascii; format=flowed\r\nContent-Transfer-Encoding: 7bit\r\nX-Authentication-Info: Submitted using SMTP AUTH at out011.verizon.net from [68.162.188.232] at Tue, 20 Apr 2004 18:53:34 -0500\r\nX-eGroups-Remote-IP: 206.46.170.135\r\nFrom: Barbara Sheridan &lt;bsher213@...&gt;\r\nSubject: Re: [SHQ_Spy_Division] opinion of anime-fanfiction.net\r\nX-Yahoo-Group-Post: member; u=1533100\r\nX-Yahoo-Profile: bsher213\r\n\r\n\nThe forum feature doesn&#39;t work *figures*\nand I&#39;m an idiot because I keep calling it anime-fanfiction when it&#39;s \nanime-fiction.net\n\n-- \nBarbara Sheridan\t\n\nhttp://www.barbarasheridan.net\n\n\n\n\n"
}