{
    "userId": 1533100,
    "authorName": "Barbara Sheridan",
    "from": "Barbara Sheridan &lt;bsher213@...&gt;",
    "profile": "bsher213",
    "replyTo": "LIST",
    "senderId": "kfqq6uaQ-xQy3uW4mPdlXhSN_GA8HFUuBj_-BRU3Ppi4eKFo0EJiPt6_9DjCx2fL5AsR0Ten7gekf1PW2XxFXO7g7ZT-BbguBFILFKseWfbjFIw",
    "spamInfo": {
        "isSpam": false,
        "reason": "0"
    },
    "subject": "Re: [SHQ] Re: Book recommendation",
    "postDate": "1080172588",
    "msgId": 129,
    "canDelete": false,
    "contentTrasformed": false,
    "systemMessage": false,
    "headers": {
        "messageIdInHeader": "PDQwNjIyMDJDLjIwNTA2MDZAYmVsbGF0bGFudGljLm5ldD4=",
        "inReplyToHeader": "PGMzdDVtdisyZm1sQGVHcm91cHMuY29tPg==",
        "referencesHeader": "PGMzdDVtdisyZm1sQGVHcm91cHMuY29tPg=="
    },
    "prevInTopic": 127,
    "nextInTopic": 130,
    "prevInTime": 128,
    "nextInTime": 130,
    "topicId": 122,
    "numMessagesInTopic": 9,
    "msgSnippet": "It works with Netscape. Apparently IE doesn t like the program I used to do  the  site pages and won t always show the images. I m not sure how to fix it",
    "rawEmail": "Return-Path: &lt;bsher213@...&gt;\r\nX-Sender: bsher213@...\r\nX-Apparently-To: SHQ@yahoogroups.com\r\nReceived: (qmail 87994 invoked from network); 24 Mar 2004 23:57:09 -0000\r\nReceived: from unknown (66.218.66.217)\n  by m14.grp.scd.yahoo.com with QMQP; 24 Mar 2004 23:57:09 -0000\r\nReceived: from unknown (HELO out008.verizon.net) (206.46.170.108)\n  by mta2.grp.scd.yahoo.com with SMTP; 24 Mar 2004 23:57:08 -0000\r\nReceived: from bellatlantic.net ([141.151.162.203]) by out008.verizon.net\n          (InterMail vM.5.01.06.06 201-253-122-130-106-20030910) with ESMTP\n          id &lt;20040324235617.LPRI27801.out008.verizon.net@...&gt;\n          for &lt;SHQ@yahoogroups.com&gt;; Wed, 24 Mar 2004 17:56:17 -0600\r\nMessage-ID: &lt;4062202C.2050606@...&gt;\r\nDate: Wed, 24 Mar 2004 18:56:28 -0500\r\nUser-Agent: Mozilla/5.0 (Windows; U; Windows NT 5.1; en-US; rv:1.4) Gecko/20030624 Netscape/7.1 (ax)\r\nX-Accept-Language: en-us, en, ja\r\nMIME-Version: 1.0\r\nTo: SHQ@yahoogroups.com\r\nReferences: &lt;c3t5mv+2fml@...&gt;\r\nIn-Reply-To: &lt;c3t5mv+2fml@...&gt;\r\nContent-Type: text/plain; charset=ISO-8859-1; format=flowed\r\nContent-Transfer-Encoding: 7bit\r\nX-Authentication-Info: Submitted using SMTP AUTH at out008.verizon.net from [141.151.162.203] at Wed, 24 Mar 2004 17:56:16 -0600\r\nX-eGroups-Remote-IP: 206.46.170.108\r\nFrom: Barbara Sheridan &lt;bsher213@...&gt;\r\nSubject: Re: [SHQ] Re: Book recommendation\r\nX-Yahoo-Group-Post: member; u=1533100\r\nX-Yahoo-Profile: bsher213\r\n\r\nIt works with Netscape. Apparently IE doesn&#39;t like the program I used to \ndo  the  site pages and won&#39;t always show the images. I&#39;m not sure how \nto fix it yet...\n\nTiffany wrote:\n\n&gt;fundoshi is not showing up!\n&gt;\n&gt;\n&gt;\n&gt;visit \n&gt;\n&gt;http://groups.yahoo.com/group/SHQ_Spy_Division/\n&gt;\n&gt;our companion list featuring fanfiction/art \n&gt;Yahoo! Groups Links\n&gt;\n&gt;\n&gt;\n&gt; \n&gt;\n&gt;\n&gt;  \n&gt;\n\n-- \nBarbara Sheridan\t\n\nhttp://www.barbarasheridan.net\n\n\n\n\n"
}