{
    "userId": 108589066,
    "authorName": "Hirotada Tokugawa",
    "from": "&quot;Hirotada Tokugawa&quot; &lt;patriot014@...&gt;",
    "profile": "shimazuryu",
    "replyTo": "LIST",
    "senderId": "1C0C7DNEvny6LagaiPyyRFZfoMr7O1nMUuOmHLftcZb2f0PH9iCW0rYkHomZ_nQVYlgn5539fuAeKyceu7jXWxBN5yEqh6LQIfb-RjUBqAHlFfs",
    "spamInfo": {
        "isSpam": false,
        "reason": "12"
    },
    "subject": "Fanmail- Kondou and Hijikata want to hear from you!",
    "postDate": "1139694790",
    "msgId": 2717,
    "canDelete": false,
    "contentTrasformed": false,
    "systemMessage": false,
    "headers": {
        "messageIdInHeader": "PEJBWTEwNC1GMzBENDYyMzBCMzI3MjgxNUVBNDg2MjlGMDUwQHBoeC5nYmw+",
        "inReplyToHeader": "PGRzZGhhdCs4N2tnQGVHcm91cHMuY29tPg=="
    },
    "prevInTopic": 2716,
    "nextInTopic": 0,
    "prevInTime": 2716,
    "nextInTime": 2718,
    "topicId": 2715,
    "numMessagesInTopic": 3,
    "msgSnippet": "As part of the newly reorganized Makoto Multimedia Dojo at http://www.shinsengumihq.com/MFD.htm, there s a new radio show in production now, called The",
    "rawEmail": "Return-Path: &lt;patriot014@...&gt;\r\nX-Sender: patriot014@...\r\nX-Apparently-To: SHQ@yahoogroups.com\r\nReceived: (qmail 65382 invoked from network); 11 Feb 2006 21:53:11 -0000\r\nReceived: from unknown (66.218.67.35)\n  by m25.grp.scd.yahoo.com with QMQP; 11 Feb 2006 21:53:11 -0000\r\nReceived: from unknown (HELO hotmail.com) (65.54.175.40)\n  by mta9.grp.scd.yahoo.com with SMTP; 11 Feb 2006 21:53:11 -0000\r\nReceived: from mail pickup service by hotmail.com with Microsoft SMTPSVC;\n\t Sat, 11 Feb 2006 13:53:10 -0800\r\nMessage-ID: &lt;BAY104-F30D46230B3272815EA48629F050@...&gt;\r\nReceived: from 65.54.175.200 by by104fd.bay104.hotmail.msn.com with HTTP;\n\tSat, 11 Feb 2006 21:53:10 GMT\r\nX-Originating-Email: [patriot014@...]\r\nX-Sender: patriot014@...\r\nIn-Reply-To: &lt;dsdhat+87kg@...&gt;\r\nTo: SHQ@yahoogroups.com\r\nBcc: \r\nDate: Sun, 12 Feb 2006 06:53:10 +0900\r\nMime-Version: 1.0\r\nContent-Type: text/plain; format=flowed\r\nX-OriginalArrivalTime: 11 Feb 2006 21:53:10.0529 (UTC) FILETIME=[8CA99F10:01C62F55]\r\nX-eGroups-Msg-Info: 1:12:0:0\r\nFrom: &quot;Hirotada Tokugawa&quot; &lt;patriot014@...&gt;\r\nSubject: Fanmail- Kondou and Hijikata want to hear from you!\r\nX-Yahoo-Group-Post: member; u=108589066; y=tN8pxoYS4RgjiGv7G3wl1pURpnd1RRmqaXtSEsiVWzLwgVia_w\r\nX-Yahoo-Profile: shimazuryu\r\n\r\nAs part of the newly reorganized Makoto Multimedia Dojo at \nhttp://www.shinsengumihq.com/MFD.htm, there&#39;s a new &quot;radio show&quot; in \nproduction now, called &quot;The Kyokuchou Hour.&quot; It&#39;s hosted by Kondou and \nHijikata, but the other captains (and connected people) appear too. And they \nwant to hear from you-- so send in your fanmail to patriot014@... , \nand they&#39;ll read it on the show!\n\n-M.\n\n\n\n"
}