{
    "userId": 108589066,
    "authorName": "Hirotada Tokugawa",
    "from": "&quot;Hirotada Tokugawa&quot; &lt;patriot014@...&gt;",
    "profile": "shimazuryu",
    "replyTo": "LIST",
    "senderId": "MLP5engBiM9o9hMjDDajYMS6Um4vrcHI8YzTZjk0gdKmlMSheDKdiXhtg3uMHDWCR0UQ9bnRz6WZfUR7Mbgp8-bEIqkC2oCq3xpY7PpdKp4xl74",
    "spamInfo": {
        "isSpam": false,
        "reason": "0"
    },
    "subject": "RE: [SHQ] Tetsunosuke Ichimura",
    "postDate": "1162517019",
    "msgId": 3000,
    "canDelete": false,
    "contentTrasformed": false,
    "systemMessage": false,
    "headers": {
        "messageIdInHeader": "PEJBWTEyMi1GMzE5QjFBMDMyQjBDOUZCQTU0NjBFQjlGRkUwQHBoeC5nYmw+",
        "inReplyToHeader": "PGVpZHEwbytkbWYzQGVHcm91cHMuY29tPg=="
    },
    "prevInTopic": 2999,
    "nextInTopic": 3001,
    "prevInTime": 2999,
    "nextInTime": 3001,
    "topicId": 2999,
    "numMessagesInTopic": 3,
    "msgSnippet": "I can get you the exact sources and citations later, but off the top of my head I know for sure that Ichimura Tetsunosuke s family background has its roots in",
    "rawEmail": "Return-Path: &lt;patriot014@...&gt;\r\nX-Sender: patriot014@...\r\nX-Apparently-To: SHQ@yahoogroups.com\r\nReceived: (qmail 92964 invoked from network); 3 Nov 2006 01:24:32 -0000\r\nReceived: from unknown (66.218.67.35)\n  by m27.grp.scd.yahoo.com with QMQP; 3 Nov 2006 01:24:32 -0000\r\nReceived: from unknown (HELO bay0-omc1-s7.bay0.hotmail.com) (65.54.246.79)\n  by mta9.grp.scd.yahoo.com with SMTP; 3 Nov 2006 01:24:32 -0000\r\nReceived: from hotmail.com ([207.46.10.239]) by bay0-omc1-s7.bay0.hotmail.com with Microsoft SMTPSVC(6.0.3790.1830);\n\t Thu, 2 Nov 2006 17:23:40 -0800\r\nReceived: from mail pickup service by hotmail.com with Microsoft SMTPSVC;\n\t Thu, 2 Nov 2006 17:23:40 -0800\r\nMessage-ID: &lt;BAY122-F319B1A032B0C9FBA5460EB9FFE0@...&gt;\r\nReceived: from 207.46.10.254 by by122fd.bay122.hotmail.msn.com with HTTP;\n\tFri, 03 Nov 2006 01:23:39 GMT\r\nX-Originating-Email: [patriot014@...]\r\nX-Sender: patriot014@...\r\nIn-Reply-To: &lt;eidq0o+dmf3@...&gt;\r\nTo: SHQ@yahoogroups.com\r\nBcc: \r\nDate: Fri, 03 Nov 2006 10:23:39 +0900\r\nMime-Version: 1.0\r\nContent-Type: text/plain; format=flowed\r\nX-OriginalArrivalTime: 03 Nov 2006 01:23:40.0395 (UTC) FILETIME=[B1B43BB0:01C6FEE6]\r\nReturn-Path: patriot014@...\r\nX-eGroups-Msg-Info: 1:0:0:0\r\nFrom: &quot;Hirotada Tokugawa&quot; &lt;patriot014@...&gt;\r\nSubject: RE: [SHQ] Tetsunosuke Ichimura\r\nX-Yahoo-Group-Post: member; u=108589066; y=Cn9ioq4pxAU4hVnjvFCmacNTs7C3EBe0JYIZlw6KAkgeFV7hfA\r\nX-Yahoo-Profile: shimazuryu\r\n\r\nI can get you the exact sources and citations later, but off the top of my \nhead I know for sure that Ichimura Tetsunosuke&#39;s family background has its \nroots in the Ogaki domain of Mino Province (incidentally, a domain which \nformed part of the Imperial army in 1868). Shinsengumi member Shimada Kai \nalso had family background in that domain. Tetsunosuke was indeed part of \nShinsengumi, and Hijikata&#39;s page-- and it&#39;s because of him leaving Hakodate \nin time that the famous photo of Hijikata exists. As far as his father, I \ndon&#39;t really know.\n\nI&#39;ve heard that he died in the Seinan War around a decade later, but there \nare other people here who know Seinan better than me.\n\nFor the record, I&#39;ve always wondered what the interaction would have been \nbetween Ichimura Tetsunosuke and Inoue Taisuke, who was Kondou&#39;s page.\n\n-M.\n\n_________________________________________________________________\nFREE pop-up blocking with the new MSN Toolbar - get it now! \nhttp://toolbar.msn.click-url.com/go/onm00200415ave/direct/01/\n\n\n"
}