{
    "userId": 145759856,
    "authorName": "Kitsuno",
    "from": "&quot;Kitsuno&quot; &lt;samurai-listowner@...&gt;",
    "profile": "kitsuno",
    "replyTo": "LIST",
    "senderId": "k62o-MPJgn-JKJG3GeqViXGOs-F1aYvg-fFWM-5a-Cy0SovQ4iB4neVzSUhE4UGM0T9Dil6leUQBJBx7exBO_TjH7bhY-mxibRmC7ZlH11sieKQEpOXZqCI",
    "spamInfo": {
        "isSpam": false,
        "reason": "6"
    },
    "subject": "Re: age",
    "postDate": "1169440464",
    "msgId": 3137,
    "canDelete": false,
    "contentTrasformed": false,
    "systemMessage": false,
    "headers": {
        "messageIdInHeader": "PGVwMWVzZytlbTZlQGVHcm91cHMuY29tPg==",
        "inReplyToHeader": "PGVwMTJqditiYTdyQGVHcm91cHMuY29tPg=="
    },
    "prevInTopic": 3136,
    "nextInTopic": 3138,
    "prevInTime": 3136,
    "nextInTime": 3138,
    "topicId": 3115,
    "numMessagesInTopic": 29,
    "msgSnippet": "... Inoue Taisuke joined the ... Confirmed by this: http://www.uni-tuebingen.de/geschichte-japans/nengo_calc.htm Looks like the book is wrong. Typo?",
    "rawEmail": "Return-Path: &lt;samurai-listowner@...&gt;\r\nX-Sender: samurai-listowner@...\r\nX-Apparently-To: SHQ@yahoogroups.com\r\nReceived: (qmail 23297 invoked from network); 22 Jan 2007 04:35:13 -0000\r\nReceived: from unknown (66.218.66.167)\n  by m26.grp.scd.yahoo.com with QMQP; 22 Jan 2007 04:35:13 -0000\r\nReceived: from unknown (HELO n12c.bullet.sp1.yahoo.com) (69.147.64.111)\n  by mta6.grp.scd.yahoo.com with SMTP; 22 Jan 2007 04:35:13 -0000\r\nReceived: from [216.252.122.217] by n12.bullet.sp1.yahoo.com with NNFMP; 22 Jan 2007 04:34:26 -0000\r\nReceived: from [66.218.69.4] by t2.bullet.sp1.yahoo.com with NNFMP; 22 Jan 2007 04:34:26 -0000\r\nReceived: from [66.218.66.84] by t4.bullet.scd.yahoo.com with NNFMP; 22 Jan 2007 04:34:26 -0000\r\nDate: Mon, 22 Jan 2007 04:34:24 -0000\r\nTo: SHQ@yahoogroups.com\r\nMessage-ID: &lt;ep1esg+em6e@...&gt;\r\nIn-Reply-To: &lt;ep12jv+ba7r@...&gt;\r\nUser-Agent: eGroups-EW/0.82\r\nMIME-Version: 1.0\r\nContent-Type: text/plain; charset=&quot;ISO-8859-1&quot;\r\nContent-Transfer-Encoding: quoted-printable\r\nX-Mailer: Yahoo Groups Message Poster\r\nX-Yahoo-Newman-Property: groups-compose\r\nX-eGroups-Msg-Info: 1:6:0:0\r\nFrom: &quot;Kitsuno&quot; &lt;samurai-listowner@...&gt;\r\nSubject: Re: age\r\nX-Yahoo-Group-Post: member; u=145759856; y=Qu3qzg_5YE0B6Bw4gdwPjdfrNC79ogs1hfylzpgPYnefkg\r\nX-Yahoo-Profile: kitsuno\r\n\r\n--- In SHQ@yahoogroups.com, &quot;Seven&quot; &lt;nlf7@...&gt; wrote:\n&gt;\n&gt; \n&gt; \n&gt; 12th month =\r\nof Ansei 4 =3D January, 1858 (not 1859)\n&gt; \n&gt; I&#39;ve checked the Japanese wiki=\r\npedia, the current version says that\nInoue Taisuke joined the \n&gt; Shinsengum=\r\ni at 11 and he was 11 (by East Asian age reckoning) in Keio 3.\n&gt; \n&gt; ~Seven\n=\r\n&gt;\n\nConfirmed by this:\n\nhttp://www.uni-tuebingen.de/geschichte-japans/nengo_=\r\ncalc.htm\n\nLooks like the book is wrong. Typo?\n\n\n"
}