{
    "userId": 182392907,
    "authorName": "Tiffany",
    "from": "&quot;Tiffany&quot; &lt;secretarytocapt3@...&gt;",
    "profile": "secretarytocapt3",
    "replyTo": "LIST",
    "senderId": "u76Fvsdz444V3jk_x0o1CDXBPc7lwdyQLKnbwbyLIUIs738ZZ_0Smt83ExZqY8UvjQ6NCcbRdO3rnnGwJrnjEfDoj64Eh4BaoeQ5249KaMm7Ymk0Qw",
    "spamInfo": {
        "isSpam": false,
        "reason": "0"
    },
    "subject": "Re: Burai Sequel",
    "postDate": "1081813148",
    "msgId": 376,
    "canDelete": false,
    "contentTrasformed": false,
    "systemMessage": false,
    "headers": {
        "messageIdInHeader": "PGM1ZjlhcytwN2k1QGVHcm91cHMuY29tPg==",
        "inReplyToHeader": "PGM1ZGU4ZStiNnU2QGVHcm91cHMuY29tPg=="
    },
    "prevInTopic": 374,
    "nextInTopic": 399,
    "prevInTime": 375,
    "nextInTime": 377,
    "topicId": 345,
    "numMessagesInTopic": 5,
    "msgSnippet": "Paypal is free and easy Grace...it is also used on ebay too. Let me be frank...the translations are OK they are not scanlations though...in burai it mentions",
    "rawEmail": "Return-Path: &lt;secretarytocapt3@...&gt;\r\nX-Sender: secretarytocapt3@...\r\nX-Apparently-To: SHQ@yahoogroups.com\r\nReceived: (qmail 77897 invoked from network); 12 Apr 2004 23:39:18 -0000\r\nReceived: from unknown (66.218.66.216)\n  by m23.grp.scd.yahoo.com with QMQP; 12 Apr 2004 23:39:18 -0000\r\nReceived: from unknown (HELO n10.grp.scd.yahoo.com) (66.218.66.65)\n  by mta1.grp.scd.yahoo.com with SMTP; 12 Apr 2004 23:39:18 -0000\r\nReceived: from [66.218.67.140] by n10.grp.scd.yahoo.com with NNFMP; 12 Apr 2004 23:39:09 -0000\r\nDate: Mon, 12 Apr 2004 23:39:08 -0000\r\nTo: SHQ@yahoogroups.com\r\nMessage-ID: &lt;c5f9as+p7i5@...&gt;\r\nIn-Reply-To: &lt;c5de8e+b6u6@...&gt;\r\nUser-Agent: eGroups-EW/0.82\r\nMIME-Version: 1.0\r\nContent-Type: text/plain; charset=ISO-8859-1\r\nContent-Length: 820\r\nX-Mailer: Yahoo Groups Message Poster\r\nX-eGroups-Remote-IP: 66.218.66.65\r\nFrom: &quot;Tiffany&quot; &lt;secretarytocapt3@...&gt;\r\nSubject: Re: Burai Sequel\r\nX-Yahoo-Group-Post: member; u=182392907\r\nX-Yahoo-Profile: secretarytocapt3\r\n\r\nPaypal is free and easy Grace...it is also used on ebay too.\n\nLet me be frank...the translations are OK they are not scanlations\nthough...in burai it mentions that Saitou washes and IRONS his fundoshi:)\nand burai makes a big deal about his stomache ache\n\n--- In SHQ@yahoogroups.com, &quot;Grace Battista&quot; &lt;mg_batt@y...&gt; wrote:\n&gt; I&#39;d been eyeing this site for a while now. It sucks though because I \n&gt; don&#39;t have paypal. Does anyone have a paypal account? I&#39;ll send you a \n&gt; check, then you&#39;ll wait for it to clear before paypal&#39;ng the said \n&gt; site.... The site says we can share the password, so.... Anyone?\n&gt; \n&gt; --- In SHQ@yahoogroups.com, &quot;Tiffany&quot; &lt;tnamwong@w...&gt; wrote:\n&gt; &gt; Matokakusei Burai (1-2\n&gt; &gt; by Youko Iwasaki\n&gt; &gt; \n&gt; &gt; Scans are available at \n&gt; &gt; http://milady.anime.pl/en/manga.php\n&gt; &gt; \n&gt; &gt; [site contains yaoi]\n\n\n"
}