{
    "userId": 176730856,
    "authorName": "GCW",
    "from": "GCW &lt;saitohworship@...&gt;",
    "profile": "saitohworship",
    "replyTo": "LIST",
    "senderId": "F8g5f68jqc-vxKrh1R_EHl-EdqGawzkcGnqPQfKYo_bqZbBXp_NOG4c4mGu970p221w_1DvcU1TRK93c_ikffa7WbUE",
    "spamInfo": {
        "isSpam": false,
        "reason": "0"
    },
    "subject": "Re: [SHQ] Grace--Re: Sasaki Tadasaburo / Saitou connection?",
    "postDate": "1082340229",
    "msgId": 470,
    "canDelete": false,
    "contentTrasformed": false,
    "systemMessage": false,
    "headers": {
        "messageIdInHeader": "PDIwMDQwNDE5MDIwMzQ5LjM1OTg3LnFtYWlsQHdlYjIwNzI4Lm1haWwueWFob28uY29tPg==",
        "inReplyToHeader": "PDQwN0QyOUU4LjkwNjA0MDhAYmVsbGF0bGFudGljLm5ldD4="
    },
    "prevInTopic": 412,
    "nextInTopic": 473,
    "prevInTime": 469,
    "nextInTime": 471,
    "topicId": 377,
    "numMessagesInTopic": 23,
    "msgSnippet": "All right, that s it.  I REALLY have to ask this.  I only get cable, but it seems that there is a tv show called Shisengumi! on one of my tv channels (ch. 35)",
    "rawEmail": "Return-Path: &lt;saitohworship@...&gt;\r\nX-Sender: saitohworship@...\r\nX-Apparently-To: SHQ@yahoogroups.com\r\nReceived: (qmail 29204 invoked from network); 19 Apr 2004 02:03:50 -0000\r\nReceived: from unknown (66.218.66.166)\n  by m17.grp.scd.yahoo.com with QMQP; 19 Apr 2004 02:03:50 -0000\r\nReceived: from unknown (HELO web20728.mail.yahoo.com) (216.136.226.118)\n  by mta5.grp.scd.yahoo.com with SMTP; 19 Apr 2004 02:03:49 -0000\r\nMessage-ID: &lt;20040419020349.35987.qmail@...&gt;\r\nReceived: from [66.53.51.42] by web20728.mail.yahoo.com via HTTP; Sun, 18 Apr 2004 19:03:49 PDT\r\nDate: Sun, 18 Apr 2004 19:03:49 -0700 (PDT)\r\nTo: SHQ@yahoogroups.com\r\nIn-Reply-To: &lt;407D29E8.9060408@...&gt;\r\nMIME-Version: 1.0\r\nX-eGroups-Remote-IP: 216.136.226.118\r\nFrom: GCW &lt;saitohworship@...&gt;\r\nSubject: Re: [SHQ] Grace--Re: Sasaki Tadasaburo / Saitou connection?\r\nX-Yahoo-Group-Post: member; u=176730856\r\nX-Yahoo-Profile: saitohworship\r\nContent-Type: text/plain\r\nContent-Transfer-Encoding: quoted-printable\r\n\r\nAll right, that&#39;s it.  I REALLY have to ask this.  I only get cable, but it=\r\n seems that there is a tv show called Shisengumi! on one of my tv channels =\r\n(ch. 35) that is NOT NHK.  So I was sondering if this is the same show (not=\r\ne the name) or another one.  This channel 35 is not purely Japanese, but th=\r\nere&#39;s also Chinese, Korean, and Vietnamese languages and shows at different=\r\n times (all asian, in short).  If anybody else lives in Southern CA and can=\r\n tell me if it&#39;s the same tv show as the one on NHK, I would greatly apprec=\r\niate it!  It has english subtitles, BTW ^ ^;;;\n \n~Saitohworship\n\n\t\t\n-------=\r\n--------------------------\nDo you Yahoo!?\nYahoo! Photos: High-quality 4x6 d=\r\nigital prints for 25=A2\n\n[Non-text portions of this message have been remov=\r\ned]\n\n\n"
}