{
    "userId": 1533100,
    "authorName": "Barbara Sheridan",
    "from": "Barbara Sheridan &lt;bsher213@...&gt;",
    "profile": "bsher213",
    "replyTo": "LIST",
    "senderId": "z5ZUPGfGOCGMOgwkeAeLR12NV3JrrPgUl2EvvkWtWXuWrIxTRGAEaTE8h12w9ZBpnAawfI-Yu7VSBT-dl-R7IXn26wdLyMty_z5KOr5sk_jZxAI",
    "spamInfo": {
        "isSpam": false,
        "reason": "0"
    },
    "subject": "Re: [SHQ] PMK Saitou Manga Ques. URGENT",
    "postDate": "1083349366",
    "msgId": 627,
    "canDelete": false,
    "contentTrasformed": false,
    "systemMessage": false,
    "headers": {
        "messageIdInHeader": "PDQwOTI5OTc2LjEwNzA4MDJAYmVsbGF0bGFudGljLm5ldD4=",
        "inReplyToHeader": "PDIwMDQwNDMwMTY1NzE1LjUyNTYyLnFtYWlsQHdlYjUwNDA4Lm1haWwueWFob28uY29tPg==",
        "referencesHeader": "PDIwMDQwNDMwMTY1NzE1LjUyNTYyLnFtYWlsQHdlYjUwNDA4Lm1haWwueWFob28uY29tPg=="
    },
    "prevInTopic": 624,
    "nextInTopic": 0,
    "prevInTime": 626,
    "nextInTime": 628,
    "topicId": 609,
    "numMessagesInTopic": 10,
    "msgSnippet": "... Yes, I m an ahou. For some reason I had RK stuck in my head.  Sorry -- Barbara Sheridan http://www.barbarasheridan.net",
    "rawEmail": "Return-Path: &lt;bsher213@...&gt;\r\nX-Sender: bsher213@...\r\nX-Apparently-To: SHQ@yahoogroups.com\r\nReceived: (qmail 59119 invoked from network); 30 Apr 2004 18:26:35 -0000\r\nReceived: from unknown (66.218.66.172)\n  by m24.grp.scd.yahoo.com with QMQP; 30 Apr 2004 18:26:35 -0000\r\nReceived: from unknown (HELO out014.verizon.net) (206.46.170.46)\n  by mta4.grp.scd.yahoo.com with SMTP; 30 Apr 2004 18:26:35 -0000\r\nReceived: from bellatlantic.net ([141.151.190.61]) by out014.verizon.net\n          (InterMail vM.5.01.06.06 201-253-122-130-106-20030910) with ESMTP\n          id &lt;20040430182249.EGWV5247.out014.verizon.net@...&gt;\n          for &lt;SHQ@yahoogroups.com&gt;; Fri, 30 Apr 2004 13:22:49 -0500\r\nMessage-ID: &lt;40929976.1070802@...&gt;\r\nDate: Fri, 30 Apr 2004 14:22:46 -0400\r\nUser-Agent: Mozilla/5.0 (Windows; U; Windows NT 5.1; en-US; rv:1.4) Gecko/20030624 Netscape/7.1 (ax)\r\nX-Accept-Language: en-us, en\r\nMIME-Version: 1.0\r\nTo: SHQ@yahoogroups.com\r\nReferences: &lt;20040430165715.52562.qmail@...&gt;\r\nIn-Reply-To: &lt;20040430165715.52562.qmail@...&gt;\r\nContent-Type: text/plain; charset=ISO-8859-1; format=flowed\r\nContent-Transfer-Encoding: 7bit\r\nX-Authentication-Info: Submitted using SMTP AUTH at out014.verizon.net from [141.151.190.61] at Fri, 30 Apr 2004 13:22:47 -0500\r\nX-eGroups-Remote-IP: 206.46.170.46\r\nFrom: Barbara Sheridan &lt;bsher213@...&gt;\r\nSubject: Re: [SHQ] PMK Saitou Manga Ques. URGENT\r\nX-Yahoo-Group-Post: member; u=1533100\r\nX-Yahoo-Profile: bsher213\r\n\r\n\n\nGCW wrote:\n\n&gt;Barb, how did u manage to download Vol 7 of Peace Maker?  Or are u talking\n&gt;about RK, since there were only 6 volumes of Shinsengumi Imon PM, and only 1\n&gt;volume of PMK?\n&gt;  \n&gt;\nYes, I&#39;m an ahou. For some reason I had RK stuck in my head.  Sorry\n\n-- \nBarbara Sheridan\nhttp://www.barbarasheridan.net\n\n\n\n\n"
}