{
    "userId": 174393936,
    "authorName": "Okita Souji",
    "from": "&quot;Okita Souji&quot; &lt;okita_souji@...&gt;",
    "profile": "okitasoji",
    "replyTo": "LIST",
    "senderId": "ZQajPNezvQJe5vafg2If9QTfCQcYpCd2517ZidWqDVeWeaQRhPZ9T_jO_bokXqbdZ80XMM1mrLYWUn91AvMVePLKo8j79hEF-p52A6hkuvjDZOk",
    "spamInfo": {
        "isSpam": false,
        "reason": "0"
    },
    "subject": "Re: [SHQ] Re: Saitou ka-mon",
    "postDate": "1084432185",
    "msgId": 706,
    "canDelete": false,
    "contentTrasformed": false,
    "systemMessage": false,
    "headers": {
        "messageIdInHeader": "PDAwMDQwMWM0MzhiOSQ0NmNlNThkMCQwMzAwYThjMEBvbW9pa2FuZT4=",
        "referencesHeader": "PDIwMDQwNTEzMDY0NjU0LjMzNzkxLnFtYWlsQHdlYjIxNDAxLm1haWwueWFob28uY29tPg=="
    },
    "prevInTopic": 705,
    "nextInTopic": 708,
    "prevInTime": 705,
    "nextInTime": 707,
    "topicId": 696,
    "numMessagesInTopic": 16,
    "msgSnippet": "No prob. Ahh ok, that makes sense now. Thanks for clearing that up. ^_^. ... From: spiritus saitou To: SHQ@yahoogroups.com Sent: Wednesday, May 12, 2004 11:46",
    "rawEmail": "Return-Path: &lt;okita_souji@...&gt;\r\nX-Sender: okita_souji@...\r\nX-Apparently-To: SHQ@yahoogroups.com\r\nReceived: (qmail 13770 invoked from network); 13 May 2004 07:11:29 -0000\r\nReceived: from unknown (66.218.66.217)\n  by m25.grp.scd.yahoo.com with QMQP; 13 May 2004 07:11:29 -0000\r\nReceived: from unknown (HELO server1.01domain.net) (209.197.236.44)\n  by mta2.grp.scd.yahoo.com with SMTP; 13 May 2004 07:11:29 -0000\r\nReceived: from lsanca1-ar58-4-40-034-061.lsanca1.dsl-verizon.net ([4.40.34.61] helo=omoikane)\n\tby server1.01domain.net with smtp (Exim 4.24)\n\tid 1BOALr-0003WC-4k\n\tfor SHQ@yahoogroups.com; Thu, 13 May 2004 01:09:55 -0600\r\nMessage-ID: &lt;000401c438b9$46ce58d0$0300a8c0@omoikane&gt;\r\nTo: &lt;SHQ@yahoogroups.com&gt;\r\nReferences: &lt;20040513064654.33791.qmail@...&gt;\r\nDate: Thu, 13 May 2004 00:09:45 -0700\r\nMIME-Version: 1.0\r\nX-Priority: 3\r\nX-MSMail-Priority: Normal\r\nX-Mailer: Microsoft Outlook Express 6.00.2800.1409\r\nX-MimeOLE: Produced By Microsoft MimeOLE V6.00.2800.1409\r\nX-AntiAbuse: This header was added to track abuse, please include it with any abuse report\r\nX-AntiAbuse: Primary Hostname - server1.01domain.net\r\nX-AntiAbuse: Original Domain - yahoogroups.com\r\nX-AntiAbuse: Originator/Caller UID/GID - [47 12] / [47 12]\r\nX-AntiAbuse: Sender Address Domain - otakuoutpost.com\r\nX-eGroups-Remote-IP: 209.197.236.44\r\nFrom: &quot;Okita Souji&quot; &lt;okita_souji@...&gt;\r\nSubject: Re: [SHQ] Re: Saitou ka-mon\r\nX-Yahoo-Group-Post: member; u=174393936\r\nX-Yahoo-Profile: okitasoji\r\nContent-Type: text/plain; charset=US-ASCII\r\nContent-Transfer-Encoding: 7bit\r\n\r\nNo prob. \n\nAhh ok, that makes sense now. Thanks for clearing that up. ^_^.\n\n  ----- Original Message ----- \n  From: spiritus saitou \n  To: SHQ@yahoogroups.com \n  Sent: Wednesday, May 12, 2004 11:46 PM\n  Subject: Re: [SHQ] Re: Saitou ka-mon\n\n\n  Okita Souji &lt;okita_souji@...&gt; wrote:\n  &gt;&gt;Out of curiosity, why would his kamon have been wisteria? &lt;&lt;\n\n  My understanding is that &quot;fuji&quot; means &quot;wisteria.&quot;  That&#39;s why I connected wisteria with the Fujita mon... simply because of the meaning of the name itself.\n\n  Thanks for all the info!!!\n\n  phil\n\n              \n  ---------------------------------\n  Do you Yahoo!?\n  Yahoo! Movies - Buy advance tickets for &#39;Shrek 2&#39; \n\n  [Non-text portions of this message have been removed]\n\n\n\n  visit \n\n  http://groups.yahoo.com/group/SHQ_Spy_Division/\n\n  our companion list featuring fanfiction/art \n\n\n        Yahoo! Groups Sponsor \n              ADVERTISEMENT\n             \n       \n       \n\n\n------------------------------------------------------------------------------\n  Yahoo! Groups Links\n\n    a.. To visit your group on the web, go to:\n    http://groups.yahoo.com/group/SHQ/\n      \n    b.. To unsubscribe from this group, send an email to:\n    SHQ-unsubscribe@yahoogroups.com\n      \n    c.. Your use of Yahoo! Groups is subject to the Yahoo! Terms of Service. \n\n\n\n[Non-text portions of this message have been removed]\n\n\n"
}